Metadata-Version: 2.4
Name: hfcrypt
Version: 2.1.0
Summary: Host encrypted apps on Hugging Face Spaces
Requires-Dist: click
Requires-Dist: huggingface-hub
Requires-Dist: cryptography
Requires-Dist: requests
Dynamic: description
Dynamic: description-content-type
Dynamic: requires-dist
Dynamic: summary
